virtucli/__init__.py
virtucli/__main__.py
virtucli/api/__init__.py
virtucli/api/api.py
virtucli/functions/__init__.py
virtucli/functions/list_vm.py
virtucli/functions/vdf.py
virtucli/functions/vm_info.py
virtucli/main.py
virtucli-0.8.3.dist-info/METADATA
virtucli-0.8.3.dist-info/WHEEL
virtucli-0.8.3.dist-info/entry_points.txt
virtucli-0.8.3.dist-info/RECORD
