Metadata-Version: 2.4
Name: virtucli
Version: 0.8.3
Summary: Basic management of Virtualizor VMs from CLI.
Author: Hendra Manudinata
Author-email: manoedinata@gmail.com
Requires-Python: >=3.10
Classifier: Programming Language :: Python :: 3
Classifier: Programming Language :: Python :: 3.10
Classifier: Programming Language :: Python :: 3.11
Classifier: Programming Language :: Python :: 3.12
Classifier: Programming Language :: Python :: 3.13
Classifier: Programming Language :: Python :: 3.14
Requires-Dist: appdirs (>=1.4.4,<2.0.0)
Requires-Dist: tabulate (>=0.9.0,<0.10.0)
